{
  "marginAccount_001": "请输入借款数量",
  "marginAccount_002": "最大",
  "marginAccount_003": "最大可借数量",
  "marginAccount_004": "小时利率",
  "marginAccount_005": "借入资产时会立即产生1小时的利息，并且每小时会计息一次（不满1小时按照1小时计算）",
  "marginAccount_006": "已借",
  "marginAccount_007": "利率和限额信息",
  "marginAccount_008": "查看",
  "marginAccount_009": "搜索历史",
  "marginAccount_010": "清除",
  "marginAccount_011": "币种列表",
  "marginAccount_012": "不可借款",
  "marginAccount_013": "查看资产",
  "marginAccount_014": "借款",
  "marginAccount_015": "还款",
  "marginAccount_016": "清除成功",
  "marginAccount_017": "成功借出$[num] $[coinName]，资产已更新。",
  "marginAccount_018": "成功还款$[num] $[coinName]，资产已更新。",
  "marginAccount_019": "逐仓币对",
  "marginAccount_020": "请输入还款数量",
  "marginAccount_021": "最大可还数量",
  "marginAccount_022": "可用余额",
  "marginAccount_023": "利息",
  "marginAccount_024": "目前杠杆档位",
  "marginAccount_025": "档位$[ladder]",
  "marginAccount_026": "总负债",
  "marginAccount_027": "币对列表",
  "marginAccount_028": "当前账户无资产，请先划转交易。",
  "marginAccount_029": "借贷利率和全仓限额",
  "marginAccount_030": "能否转入",
  "marginAccount_031": "能否借款",
  "marginAccount_032": "日利率/年利率",
  "marginAccount_033": "借贷限额",
  "marginAccount_034": "查看档位信息",
  "marginAccount_035": "杠杆倍数",
  "marginAccount_036": "有效倍数",
  "marginAccount_037": "初始风险率",
  "marginAccount_038": "强平风险率",
  "marginAccount_039": "计价币最大可借",
  "marginAccount_040": "标的币最大可借",
  "marginAccount_041": "我们可能会在极端市场波动时暂停某币种的借贷功能",
  "marginAccount_042": "当前杠杆档位满额借币时的初始风险率。",
  "marginAccount_043": "交易对",
  "marginAccount_044": "搜索币对",
  "marginAccount_045": "全仓",
  "marginAccount_046": "逐仓",
  "marginAccount_047": "逐仓交易对",
  "marginAccount_048": "逐仓档位信息",
  "marginAccount_049": "平仓下单$[tradeName] 逐仓仓位",
  "marginAccount_050": "负债金额",
  "marginAccount_051": "您的计价币种存在负债。市价一键平仓可能无法完全偿还欠款。",
  "marginAccount_052": "优先使用可用资产还款。并根据剩余负债下市价自动还款单。市价单可能无法确保获得的资产金额，使用一键平仓退出大额仓位可能导致损失。一键平仓仅收取交易费用。",
  "marginAccount_053": "您的剩余负债金额太小不足以进行下单，请手动进行平仓还款操作。",
  "marginAccount_054": "平仓提交成功",
  "marginAccount_055": "全仓账户",
  "marginAccount_056": "逐仓账户",
  "marginAccount_057": "一键平仓",
  "marginAccount_058": "净资产",
  "marginAccount_059": "借款/还款",
  "marginAccount_060": "手动借款",
  "marginAccount_061": "自动借款",
  "marginAccount_062": "手动还款",
  "marginAccount_063": "自动还款",
  "marginAccount_064": "强平还款",
  "marginAccount_065": "日利率",
  "marginAccount_066": "强平开始时间",
  "marginAccount_067": "平仓时风险率",
  "marginAccount_068": "平仓时总资产估值（USDT）",
  "marginAccount_069": "平仓时总负债估值（USDT）",
  "marginAccount_070": "强平清算费用估值（USDT）",
  "marginAccount_071": "强平结束时间",
  "marginAccount_072": "关联强平订单",
  "marginAccount_073": "只展示三个月内的记录",
  "marginAccount_074": "自动借款指杠杆交易时使用自动借款功能产生",
  "marginAccount_075": "自动还款指杠杆交易时使用自动还款功能产生的还款",
  "marginAccount_076": "全部币种",
  "marginAccount_077": "全部币对",
  "marginAccount_078": "借款记录",
  "marginAccount_079": "还款记录",
  "marginAccount_080": "利息记录",
  "marginAccount_081": "强平纪录",
  "marginAccount_082": "截止日期须大于起始日期",
  "marginAccount_083": "日期无效",
  "marginAccount_084": "强平订单",
  "marginAccount_085": "买入",
  "marginAccount_086": "卖出",
  "marginAccount_087": "委托时间",
  "marginAccount_088": "委托类型",
  "marginAccount_089": "限价委托",
  "marginAccount_090": "市价委托",
  "marginAccount_091": "计划委托",
  "marginAccount_092": "委托量",
  "marginAccount_093": "成交数量",
  "marginAccount_094": "委托价格",
  "marginAccount_095": "市价",
  "marginAccount_096": "成交均价",
  "marginAccount_097": "未成交",
  "marginAccount_098": "部分成交",
  "marginAccount_099": "完全成交",
  "marginAccount_100": "撤单处理中",
  "marginAccount_101": "未触发",
  "marginAccount_102": "已触发",
  "marginAccount_103": "部分成交已撤单",
  "marginAccount_104": "强平成交明细",
  "marginAccount_105": "成交时间",
  "marginAccount_106": "成交价格",
  "marginAccount_107": "全仓杠杆账户",
  "marginAccount_108": "杠杆账户中超过$[times]倍负债估值的部分可转出",
  "marginAccount_109": "不可划转",
  "marginAccount_110": "操作成功,请等待审核",
  "marginAccount_111": "去杠杆交易",
  "marginAccount_112": "去币币交易",
  "marginAccount_113": "逐仓杠杆账户"
}
